{
  "projects": [
    {
      "name": "projeto front-end",
      "budget": "12000",
      "category": {
        "id": "4",
        "name": "Planejamento"
      },
      "coManager": 0,
      "services": [],
      "id": 1
    },
    {
      "name": "projeto back end",
      "budget": "10000",
      "category": {
        "id": "3",
        "name": "Design"
      },
      "coManager": 0,
      "services": [],
      "id": 2
    },
    {
      "name": "Landing Page Loja 1 ",
      "budget": "10000",
      "category": {
        "id": "3",
        "name": "Design"
      },
      "coManager": 0,
      "services": [],
      "id": 3
    }
  ],
  "categories": [
    {
      "id": 1,
      "name": "infra"
    },
    {
      "id": 2,
      "name": "Desenvolvimento"
    },
    {
      "id": 3,
      "name": "Design"
    },
    {
      "id": 4,
      "name": "Planejamento"
    },
    {
      "id": 5,
      "name": "Fron-end"
    }
  ]
}